victor/__init__.py
victor/api.py
victor/presenter.py
victor/victor.py
victor-0.1.1.dist-info/DESCRIPTION.rst
victor-0.1.1.dist-info/METADATA
victor-0.1.1.dist-info/RECORD
victor-0.1.1.dist-info/WHEEL
victor-0.1.1.dist-info/metadata.json
victor-0.1.1.dist-info/top_level.txt
