Metadata-Version: 2.0
Name: victor
Version: 0.1.1
Summary: A simple tool for debugging and profiling applications
Home-page: https://github.com/jcomo/victor
Author: Jonathan Como
Author-email: jonathan.como@gmail.com
License: UNKNOWN
Keywords: debug profile python test
Platform: UNKNOWN
Classifier: Programming Language :: Python :: 2
Classifier: Programming Language :: Python :: 2.6
Classifier: Programming Language :: Python :: 2.7
Classifier: Programming Language :: Python :: 3.3
Classifier: Programming Language :: Python :: 3.4
Requires-Dist: six (>=1.10)
